common_ai_core/__init__.py
common_ai_core/chat.py
common_ai_core/exceptions.py
common_ai_core/logger.py
common_ai_core/memory.py
common_ai_core/providers.py
common_ai_core/types.py
common_ai_core/parsers/__init__.py
common_ai_core/parsers/code_parser.py
common_ai_core/parsers/json_parser.py
common_ai_core/parsers/json_validator.py
common_ai_core/tokens/__init__.py
common_ai_core/tokens/token_counter.py
common_ai_core/tokens/token_tracker.py
common_ai_core-0.1.4.dist-info/METADATA
common_ai_core-0.1.4.dist-info/WHEEL
common_ai_core-0.1.4.dist-info/licenses/LICENSE
common_ai_core-0.1.4.dist-info/RECORD
