Metadata-Version: 2.4
Name: common-ai-core
Version: 0.1.4
Summary: A flexible Python framework for building AI chat applications with support for multiple LLM providers including OpenAI, Anthropic, Gemini, DeepSeek, and local Llama models
Author-email: Helge Moden <helgemod@gmail.com>
Maintainer-email: Helge Moden <helgemod@gmail.com>
License-Expression: MIT
License-File: LICENSE
Keywords: ai,anthropic,artificial-intelligence,chat,claude,deepseek,gemini,gpt,json-parsing,language-model,llama,llm,memory,openai,reasoning,streaming,token-counting
Classifier: Development Status :: 4 - Beta
Classifier: Framework :: Pytest
Classifier: Intended Audience :: Developers
Classifier: Intended Audience :: Science/Research
Classifier: License :: OSI Approved :: MIT License
Classifier: Operating System :: OS Independent
Classifier: Programming Language :: Python :: 3
Classifier: Programming Language :: Python :: 3.8
Classifier: Programming Language :: Python :: 3.9
Classifier: Programming Language :: Python :: 3.10
Classifier: Programming Language :: Python :: 3.11
Classifier: Programming Language :: Python :: 3.12
Classifier: Topic :: Communications :: Chat
Classifier: Topic :: Scientific/Engineering :: Artificial Intelligence
Classifier: Topic :: Software Development :: Libraries :: Python Modules
Classifier: Topic :: Text Processing :: Linguistic
Classifier: Typing :: Typed
Requires-Python: >=3.8
Requires-Dist: openai>=1.0.0
Requires-Dist: tiktoken>=0.3.0
Provides-Extra: all
Requires-Dist: anthropic>=0.3.0; extra == 'all'
Requires-Dist: google-generativeai>=0.3.0; extra == 'all'
Requires-Dist: llama-cpp-python>=0.2.0; extra == 'all'
Requires-Dist: openai>=1.0.0; extra == 'all'
Provides-Extra: all-cloud
Requires-Dist: anthropic>=0.3.0; extra == 'all-cloud'
Requires-Dist: google-generativeai>=0.3.0; extra == 'all-cloud'
Requires-Dist: openai>=1.0.0; extra == 'all-cloud'
Provides-Extra: anthropic
Requires-Dist: anthropic>=0.3.0; extra == 'anthropic'
Provides-Extra: deepseek
Requires-Dist: openai>=1.0.0; extra == 'deepseek'
Provides-Extra: dev
Requires-Dist: black>=22.0; extra == 'dev'
Requires-Dist: isort>=5.0; extra == 'dev'
Requires-Dist: pytest>=7.0; extra == 'dev'
Provides-Extra: gemini
Requires-Dist: google-generativeai>=0.3.0; extra == 'gemini'
Provides-Extra: llama
Requires-Dist: llama-cpp-python>=0.2.0; extra == 'llama'
